{
  "$schema": "http://json-schema.org/draft-07/schema",
  "$id": "https://eodash.github.io/eodash-schemas/catalog/catalog-schema.json",
  "type": "object",
  "format": "categories",
  "basicCategoryTitle": "General",
  "properties": {
    "id": {
      "type": "string",
      "description": "Identifier string used for the collection, no catalog should repeat the id used"
    },
    "title": {
      "type": "string",
      "description": "Title added to catalog file, shown by STAC clients"
    },
    "description": {
      "type": "string",
      "format": "markdown",
      "description": "Description added to catalog file. Markdown may be used for rich text representation."
    },
    "endpoint": {
      "type": "string",
      "description": "Expected url where catalog will be deployed"
    },
    "assets_endpoint": {
      "type": "string",
      "description": "Url base path to where locations will be deployed"
    },
    "collections": {
      "type": "array",
      "items": {
        "type": "string"
      },
      "description": "List of collections and indicators that will be part of the catalog, have to match file names of collections and indicators configured in the <b>collections</b> and <b>indicators</b> folders (without the extension)"
    },
    "default_base_layers": {
      "type": "string",
      "description": "Optional relative path to baselayer definition file. Example: layers/baselayers.json"
    },
    "default_overlay_layers": {
      "type": "string",
      "description": "Optional relative path to overlay definition file. Example: layers/overlays.json"
    }
  },
  "required": [
    "id",
    "title",
    "description",
    "endpoint",
    "assets_endpoint",
    "collections"
  ]
}